<?xml version="1.0" encoding="UTF-8"?>

<bean>
  <title>Centro</title>
  <data_source>Centro</data_source>
  <order_by/>
  <primary_key>
    <item>ID</item>
  </primary_key>
  <xml>
    <class>Centro</class>
  </xml>
  <attributes>
    <item>
      <name>ID</name>
      <type>1</type>
      <xml>
        <name>ID</name>
        <class/>
      </xml>
    </item>
    <item>
      <name>recapiti_centro</name>
      <type>1</type>
      <xml>
        <name>recapiti_centro</name>
        <class/>
      </xml>
    </item>
    <item>
      <name>nome_centro</name>
      <type>1</type>
      <xml>
        <name>nome_centro</name>
        <class/>
      </xml>
    </item>
    <item>
      <name>email_centro</name>
      <type>1</type>
      <xml>
        <name>email_centro</name>
        <class/>
      </xml>
    </item>
    <item>
      <name>percorsi_centro</name>
      <type>8</type>
      <xml>
        <name>percorsi_centro</name>
        <class>Percorso</class>
        <relationship>1-N</relationship>
        <target>centro</target>
        <foreign_class>Centro</foreign_class>
      </xml>
      <codomain>Percorso</codomain>
      <from>ID</from>
      <to>ID_Centro_percorsi_centro</to>
    </item>
  </attributes>
</bean>
